ragpack/__init__.py
genrag-0.1.0.dist-info/LICENSE.txt
genrag-0.1.0.dist-info/METADATA
genrag-0.1.0.dist-info/WHEEL
genrag-0.1.0.dist-info/top_level.txt
genrag-0.1.0.dist-info/RECORD
