Metadata-Version: 2.1
Name: genrag
Version: 0.1.0
Summary: It is a rag standalone package
Home-page: UNKNOWN
Author: gangadhar
Author-email: gangadhartarun21@gmail.com
License: UNKNOWN
Platform: UNKNOWN
Classifier: Programming Language :: Python :: 3
Classifier: License :: OSI Approved :: MIT License
Classifier: Operating System :: OS Independent
License-File: LICENSE.txt
Requires-Dist: transformers==4.41.0
Requires-Dist: datasets==3.2.0
Requires-Dist: fsspec==2024.9.0
Requires-Dist: openai==0.28.0
Requires-Dist: faiss-cpu==1.9.0.post1
